[
{"events": [{"day": "15", "month": "NOV", "event_name": "GLITZ", "link": "https://o-klub.at/event-type/youando/"}, {"day": "16", "month": "NOV", "event_name": "Super Disco", "link": "https://o-klub.at/event-type/superdisco/"}, {"day": "22", "month": "NOV", "event_name": "MARCO FARAONE", "link": "https://o-klub.at/event-type/solid-gold/"}, {"day": "22", "month": "NOV", "event_name": "HYPE!", "link": "https://o-klub.at/event-type/oz/"}, {"day": "23", "month": "NOV", "event_name": "Super Disco", "link": "https://o-klub.at/event-type/hype/"}, {"day": "29", "month": "NOV", "event_name": "HYPE!", "link": "https://o-klub.at/event-type/glitz/"}, {"day": "30", "month": "NOV", "event_name": "Super Disco", "link": "https://o-klub.at/events/glitz-2/"}, {"day": "6", "month": "DEZ", "event_name": "Kevin De Vries", "link": "https://o-klub.at/events/super-disco-10/"}, {"day": "07", "month": "DEZ", "event_name": "Super Disco", "link": "https://o-klub.at/events/marco-faraone-2/"}, {"day": "13", "month": "DEZ", "event_name": "MAJA x BAZAR", "link": "https://o-klub.at/events/hype-5-2/"}, {"day": "14", "month": "DEZ", "event_name": "Super Disco", "link": "https://o-klub.at/events/super-disco-11/"}, {"day": "20", "month": "DEZ", "event_name": "GLITZ", "link": "https://o-klub.at/events/hype-7/"}, {"day": "21", "month": "DEZ", "event_name": "Super Disco", "link": "https://o-klub.at/events/super-disco-12/"}, {"day": "28", "month": "DEZ", "event_name": "Super Disco", "link": "https://o-klub.at/events/kevin-de-vries/"}, {"day": "31", "month": "DEZ", "event_name": "Super Raketen Disco", "link": "https://o-klub.at/events/super-disco/"}, {"day": "17", "month": "JAN", "event_name": "GLITZ", "link": "https://o-klub.at/events/7312/"}]}
]